yingbox/__init__.py
yingbox/ez_cleaning.py
yingbox/matplotlib_helpers.py
yingbox/mongo_helpers.py
yingbox/sklearn_helpers.py
yingbox/utilities.py
yingbox-0.0.5.dist-info/LICENSE
yingbox-0.0.5.dist-info/METADATA
yingbox-0.0.5.dist-info/WHEEL
yingbox-0.0.5.dist-info/top_level.txt
yingbox-0.0.5.dist-info/RECORD
