Metadata-Version: 2.1
Name: yingbox
Version: 0.0.5
Summary: Ying's data science helper functions
Home-page: https://github.com/mathyingzhou/yingbox
Author: Ying Zhou
Author-email: yingzhou474@gmail.com
License: UNKNOWN
Platform: UNKNOWN
Classifier: Programming Language :: Python :: 3
Classifier: License :: OSI Approved :: MIT License
Classifier: Operating System :: OS Independent
Requires-Python: >=3.6
Requires-Dist: pandas
Requires-Dist: pymongo
Requires-Dist: scikit-learn
